alfredo_test_package/__init__.py
alfredo_test_package/module_dummy.py
alfredo_test_package-0.1.4.dist-info/METADATA
alfredo_test_package-0.1.4.dist-info/WHEEL
alfredo_test_package-0.1.4.dist-info/licenses/LICENSE
alfredo_test_package-0.1.4.dist-info/RECORD
